Workbook

Sheet BS
A1: 帳票名：残高試算表(年間推移)
A3: 事業所名：株式会社マザースマイル
A4: 税抜/税込：税抜
A6: 勘定科目 | B6: =VLOOKUP(A6,Sheet1!$A$1:$B$242,2,FALSE) -> 계정과목 | C6: 4月度 | D6: 5月度 | E6: 6月度 | F6: 7月度 | G6: 8月度 | H6: 9月度 | I6: 上半期残高(合計) | J6: 10月度 | K6: 11月度 | L6: 12月度 | M6: 1月度 | N6: 2月度 | O6: 3月度 | P6: 下半期残高(合計) | Q6: 当期仮残高(合計) | R6: 決算残高(合計) | S6: 当期残高(合計)
A7: [現金･預金] | B7: =VLOOKUP(A7,Sheet1!$A$1:$B$242,2,FALSE) -> [현금･예금]
A8: 現金 | B8: =VLOOKUP(A8,Sheet1!$A$1:$B$242,2,FALSE) -> 현금 | C8: 129534 | D8: 80197 | E8: 252530 | F8: 228130 | G8: 254588 | H8: 98075 | I8: 98075 | J8: 220062 | K8: 19207 | L8: 413805 | M8: 413805 | N8: 413805 | O8: 413805 | P8: 413805 | Q8: 413805 | R8: 413805 | S8: 413805
A9: 普通預金 | B9: =VLOOKUP(A9,Sheet1!$A$1:$B$242,2,FALSE) -> 보통예금 | C9: 13780845 | D9: 10920496 | E9: 16156649 | F9: 22398432 | G9: 30896250 | H9: 24328317 | I9: 24328317 | J9: 41514483 | K9: 46556239 | L9: 49866189 | M9: 49866189 | N9: 49866189 | O9: 49866189 | P9: 49866189 | Q9: 49866189 | R9: 49866189 | S9: 49866189
A10: 現金･預金合計 | B10: =VLOOKUP(A10,Sheet1!$A$1:$B$242,2,FALSE) -> 현금 ･예금합계 | C10: 13910379 | D10: 11000693 | E10: 16409179 | F10: 22626562 | G10: 31150838 | H10: 24426392 | I10: 24426392 | J10: 41734545 | K10: 46575446 | L10: 50279994 | M10: 50279994 | N10: 50279994 | O10: 50279994 | P10: 50279994 | Q10: 50279994 | R10: 50279994 | S10: 50279994
A11: [売上債権] | B11: =VLOOKUP(A11,Sheet1!$A$1:$B$242,2,FALSE) -> [매출채권]
A12: 売掛金 | B12: =VLOOKUP(A12,Sheet1!$A$1:$B$242,2,FALSE) -> 외상매출금 | C12: 16474507 | D12: 18116551 | E12: 25087039 | F12: 22265770 | G12: 20381384 | H12: 35647802 | I12: 35647802 | J12: 26503906 | K12: 33157239 | L12: 50784726 | M12: 50784726 | N12: 50784726 | O12: 50784726 | P12: 50784726 | Q12: 50784726 | R12: 50784726 | S12: 50784726
A13: 貸倒引当金(売) | B13: =VLOOKUP(A13,Sheet1!$A$1:$B$242,2,FALSE) -> 대손충당금 | C13: -206241 | D13: -206241 | E13: -206241 | F13: -206241 | G13: -206241 | H13: -206241 | I13: -206241 | J13: -206241 | K13: -206241 | L13: -507847 | M13: -507847 | N13: -507847 | O13: -507847 | P13: -507847 | Q13: -507847 | R13: -507847 | S13: -507847
A14: 売上債権合計 | B14: =VLOOKUP(A14,Sheet1!$A$1:$B$242,2,FALSE) -> 매출채권합계 | C14: 16268266 | D14: 17910310 | E14: 24880798 | F14: 22059529 | G14: 20175143 | H14: 35441561 | I14: 35441561 | J14: 26297665 | K14: 32950998 | L14: 50276879 | M14: 50276879 | N14: 50276879 | O14: 50276879 | P14: 50276879 | Q14: 50276879 | R14: 50276879 | S14: 50276879
A15: [有価証券] | B15: =VLOOKUP(A15,Sheet1!$A$1:$B$242,2,FALSE) -> [유가증권]
A16: 有価証券合計 | B16: =VLOOKUP(A16,Sheet1!$A$1:$B$242,2,FALSE) -> 유가증권합계 | C16: 0 | D16: 0 | E16: 0 | F16: 0 | G16: 0 | H16: 0 | I16: 0 | J16: 0 | K16: 0 | L16: 0 | M16: 0 | N16: 0 | O16: 0 | P16: 0 | Q16: 0 | R16: 0 | S16: 0
A17: [棚卸資産] | B17: =VLOOKUP(A17,Sheet1!$A$1:$B$242,2,FALSE) -> [재고자산]
A18: 商品 | B18: =VLOOKUP(A18,Sheet1!$A$1:$B$242,2,FALSE) -> 상품 | C18: 75443317 | D18: 72214523 | E18: 63829945 | F18: 68176813 | G18: 67522901 | H18: 47297814 | I18: 47297814 | J18: 58667847 | K18: 61842456 | L18: 72632874 | M18: 72632874 | N18: 72632874 | O18: 72632874 | P18: 72632874 | Q18: 72632874 | R18: 72632874 | S18: 72632874
A19: 棚卸資産合計 | B19: =VLOOKUP(A19,Sheet1!$A$1:$B$242,2,FALSE) -> 재고자산합계 | C19: 75443317 | D19: 72214523 | E19: 63829945 | F19: 68176813 | G19: 67522901 | H19: 47297814 | I19: 47297814 | J19: 58667847 | K19: 61842456 | L19: 72632874 | M19: 72632874 | N19: 72632874 | O19: 72632874 | P19: 72632874 | Q19: 72632874 | R19: 72632874 | S19: 72632874
A20: [他流動資産] | B20: =VLOOKUP(A20,Sheet1!$A$1:$B$242,2,FALSE) -> [기타유동자산]
A21: 前渡金 | B21: =VLOOKUP(A21,Sheet1!$A$1:$B$242,2,FALSE) -> 전도금 | C21: 270000 | D21: 270000 | E21: 4444616 | F21: 225000 | G21: 225000 | H21: 11610396 | I21: 11610396 | J21: 5398138 | K21: 217300 | L21: 14379902 | M21: 14379902 | N21: 14379902 | O21: 14379902 | P21: 14379902 | Q21: 14379902 | R21: 14379902 | S21: 14379902
A22: 立替金 | B22: =VLOOKUP(A22,Sheet1!$A$1:$B$242,2,FALSE) -> 대지급금 | C22: 906748 | D22: 453374 | E22: 0 | F22: 0 | G22: 0 | H22: 0 | I22: 0 | J22: 0 | K22: 0 | L22: 0 | M22: 0 | N22: 0 | O22: 0 | P22: 0 | Q22: 0 | R22: 0 | S22: 0
A23: 前払費用 | B23: =VLOOKUP(A23,Sheet1!$A$1:$B$242,2,FALSE) -> 선급비용 | C23: 2194113 | D23: 2542344 | E23: 2569579 | F23: 2489570 | G23: 2448609 | H23: 2485724 | I23: 2485724 | J23: 2914357 | K23: 2062663 | L23: 1804553 | M23: 1804553 | N23: 1804553 | O23: 1804553 | P23: 1804553 | Q23: 1804553 | R23: 1804553 | S23: 1804553
A24: 未収入金 | B24: =VLOOKUP(A24,Sheet1!$A$1:$B$242,2,FALSE) -> 미수입금 | C24: 29802 | D24: 29802 | E24: 105432 | F24: 346774 | G24: 588118 | H24: 588742 | I24: 588742 | J24: 1712920 | K24: 916370 | L24: 309210 | M24: 309210 | N24: 309210 | O24: 309210 | P24: 309210 | Q24: 309210 | R24: 309210 | S24: 309210
A25: 仮払金 | B25: =VLOOKUP(A25,Sheet1!$A$1:$B$242,2,FALSE) -> 가불금 | C25: 0 | D25: 600000 | E25: 0 | F25: 0 | G25: 0 | H25: 3412100 | I25: 3412100 | J25: 3412100 | K25: 3412100 | L25: 0 | M25: 0 | N25: 0 | O25: 0 | P25: 0 | Q25: 0 | R25: 0 | S25: 0
A26: 仮払消費税等 | B26: =VLOOKUP(A26,Sheet1!$A$1:$B$242,2,FALSE) -> 가불소비세등 | C26: 2268151 | D26: 4056893 | E26: 6060352 | F26: 9067690 | G26: 11286037 | H26: 13209136 | I26: 13209136 | J26: 17574794 | K26: 21851603 | L26: 0 | M26: 0 | N26: 0 | O26: 0 | P26: 0 | Q26: 0 | R26: 0 | S26: 0
A27: 他流動資産合計 | B27: =VLOOKUP(A27,Sheet1!$A$1:$B$242,2,FALSE) -> 기타유동자산합계 | C27: 5668814 | D27: 7952413 | E27: 13179979 | F27: 12129034 | G27: 14547764 | H27: 31306098 | I27: 31306098 | J27: 31012309 | K27: 28460036 | L27: 16493665 | M27: 16493665 | N27: 16493665 | O27: 16493665 | P27: 16493665 | Q27: 16493665 | R27: 16493665 | S27: 16493665
A28: 流動資産合計 | B28: =VLOOKUP(A28,Sheet1!$A$1:$B$242,2,FALSE) -> 유동자산합계 | C28: 111290776 | D28: 109077939 | E28: 118299901 | F28: 124991938 | G28: 133396646 | H28: 138471865 | I28: 138471865 | J28: 157712366 | K28: 169828936 | L28: 189683412 | M28: 189683412 | N28: 189683412 | O28: 189683412 | P28: 189683412 | Q28: 189683412 | R28: 189683412 | S28: 189683412
A29: [有形固定資産] | B29: =VLOOKUP(A29,Sheet1!$A$1:$B$242,2,FALSE) -> [유형고정자산]
A30: 車両運搬具 | B30: =VLOOKUP(A30,Sheet1!$A$1:$B$242,2,FALSE) -> 차량운반구 | C30: 28073153 | D30: 28073153 | E30: 28073153 | F30: 28073153 | G30: 28073153 | H30: 28073153 | I30: 28073153 | J30: 26196619 | K30: 26196619 | L30: 26196619 | M30: 26196619 | N30: 26196619 | O30: 26196619 | P30: 26196619 | Q30: 26196619 | R30: 26196619 | S30: 26196619
A31: 工具器具備品 | B31: =VLOOKUP(A31,Sheet1!$A$1:$B$242,2,FALSE) -> 공구기구비품 | C31: 677164 | D31: 677164 | E31: 677164 | F31: 677164 | G31: 677164 | H31: 677164 | I31: 677164 | J31: 677164 | K31: 677164 | L31: 677164 | M31: 677164 | N31: 677164 | O31: 677164 | P31: 677164 | Q31: 677164 | R31: 677164 | S31: 677164
A32: 一括償却資産 | B32: =VLOOKUP(A32,Sheet1!$A$1:$B$242,2,FALSE) -> 일괄상각자산 | C32: 133722 | D32: 133722 | E32: 133722 | F32: 133722 | G32: 133722 | H32: 133722 | I32: 133722 | J32: 133722 | K32: 133722 | L32: 33431 | M32: 33431 | N32: 33431 | O32: 33431 | P32: 33431 | Q32: 33431 | R32: 33431 | S32: 33431
A33: 減価償却累計額 | B33: =VLOOKUP(A33,Sheet1!$A$1:$B$242,2,FALSE) -> 감가상각누계액 | C33: -20741624 | D33: -20978378 | E33: -21215132 | F33: -21451886 | G33: -21688640 | H33: -21925394 | I33: -21925394 | J33: -20285615 | K33: -20522369 | L33: -20759138 | M33: -20759138 | N33: -20759138 | O33: -20759138 | P33: -20759138 | Q33: -20759138 | R33: -20759138 | S33: -20759138
A34: 有形固定資産計 | B34: =VLOOKUP(A34,Sheet1!$A$1:$B$242,2,FALSE) -> 유형고정자산계 | C34: 8142415 | D34: 7905661 | E34: 7668907 | F34: 7432153 | G34: 7195399 | H34: 6958645 | I34: 6958645 | J34: 6721890 | K34: 6485136 | L34: 6148076 | M34: 6148076 | N34: 6148076 | O34: 6148076 | P34: 6148076 | Q34: 6148076 | R34: 6148076 | S34: 6148076
A35: [無形固定資産] | B35: =VLOOKUP(A35,Sheet1!$A$1:$B$242,2,FALSE) -> [무형고정자산]
A36: 無形固定資産計 | B36: =VLOOKUP(A36,Sheet1!$A$1:$B$242,2,FALSE) -> 무형고정자산계 | C36: 0 | D36: 0 | E36: 0 | F36: 0 | G36: 0 | H36: 0 | I36: 0 | J36: 0 | K36: 0 | L36: 0 | M36: 0 | N36: 0 | O36: 0 | P36: 0 | Q36: 0 | R36: 0 | S36: 0
A37: [投資その他の資産] | B37: =VLOOKUP(A37,Sheet1!$A$1:$B$242,2,FALSE) -> [투자기타자산]
A38: 差入保証金 | B38: =VLOOKUP(A38,Sheet1!$A$1:$B$242,2,FALSE) -> 차입보증금 | C38: 4658940 | D38: 4658940 | E38: 4658940 | F38: 4658940 | G38: 4702740 | H38: 4702740 | I38: 4702740 | J38: 6836046 | K38: 4436046 | L38: 4436046 | M38: 4436046 | N38: 4436046 | O38: 4436046 | P38: 4436046 | Q38: 4436046 | R38: 4436046 | S38: 4436046
A39: 長期貸付金 | B39: =VLOOKUP(A39,Sheet1!$A$1:$B$242,2,FALSE) -> 장기대여금 | C39: 1000000 | D39: 1000000 | E39: 1000000 | F39: 1000000 | G39: 1000000 | H39: 1000000 | I39: 1000000 | J39: 1000000 | K39: 1000000 | L39: 8828000 | M39: 8828000 | N39: 8828000 | O39: 8828000 | P39: 8828000 | Q39: 8828000 | R39: 8828000 | S39: 8828000
A40: 長期前払費用 | B40: =VLOOKUP(A40,Sheet1!$A$1:$B$242,2,FALSE) -> 장기선불비용 | C40: 1393195 | D40: 1393195 | E40: 1393195 | F40: 1393195 | G40: 1393195 | H40: 1393195 | I40: 1393195 | J40: 1393195 | K40: 637368 | L40: 401500 | M40: 401500 | N40: 401500 | O40: 401500 | P40: 401500 | Q40: 401500 | R40: 401500 | S40: 401500
A41: リサイクル預託金 | B41: =VLOOKUP(A41,Sheet1!$A$1:$B$242,2,FALSE) -> 리사이클 예탁금 | C41: 67070 | D41: 67070 | E41: 67070 | F41: 67070 | G41: 67070 | H41: 67070 | I41: 67070 | J41: 58520 | K41: 58520 | L41: 58520 | M41: 58520 | N41: 58520 | O41: 58520 | P41: 58520 | Q41: 58520 | R41: 58520 | S41: 58520
A42: 投資その他の資産合計 | B42: =VLOOKUP(A42,Sheet1!$A$1:$B$242,2,FALSE) -> 투자기타자산합계 | C42: 7119205 | D42: 7119205 | E42: 7119205 | F42: 7119205 | G42: 7163005 | H42: 7163005 | I42: 7163005 | J42: 9287761 | K42: 6131934 | L42: 13724066 | M42: 13724066 | N42: 13724066 | O42: 13724066 | P42: 13724066 | Q42: 13724066 | R42: 13724066 | S42: 13724066
A43: 固定資産合計 | B43: =VLOOKUP(A43,Sheet1!$A$1:$B$242,2,FALSE) -> 고정자산합계 | C43: 15261620 | D43: 15024866 | E43: 14788112 | F43: 14551358 | G43: 14358404 | H43: 14121650 | I43: 14121650 | J43: 16009651 | K43: 12617070 | L43: 19872142 | M43: 19872142 | N43: 19872142 | O43: 19872142 | P43: 19872142 | Q43: 19872142 | R43: 19872142 | S43: 19872142
A44: [繰延資産] | B44: =VLOOKUP(A44,Sheet1!$A$1:$B$242,2,FALSE) -> [이연자산]
A45: 繰延資産合計 | B45: =VLOOKUP(A45,Sheet1!$A$1:$B$242,2,FALSE) -> 이연자산합계 | C45: 0 | D45: 0 | E45: 0 | F45: 0 | G45: 0 | H45: 0 | I45: 0 | J45: 0 | K45: 0 | L45: 0 | M45: 0 | N45: 0 | O45: 0 | P45: 0 | Q45: 0 | R45: 0 | S45: 0
A46: [諸口] | B46: =VLOOKUP(A46,Sheet1!$A$1:$B$242,2,FALSE) -> [제좌]
A47: 資産合計 | B47: =VLOOKUP(A47,Sheet1!$A$1:$B$242,2,FALSE) -> 자산합계 | C47: 126552396 | D47: 124102805 | E47: 133088013 | F47: 139543296 | G47: 147755050 | H47: 152593515 | I47: 152593515 | J47: 173722017 | K47: 182446006 | L47: 209555554 | M47: 209555554 | N47: 209555554 | O47: 209555554 | P47: 209555554 | Q47: 209555554 | R47: 209555554 | S47: 209555554
A48: [仕入債務] | B48: =VLOOKUP(A48,Sheet1!$A$1:$B$242,2,FALSE) -> [매입채무]
A49: 買掛金 | B49: =VLOOKUP(A49,Sheet1!$A$1:$B$242,2,FALSE) -> 외상매입금 | C49: 13016963 | D49: 6730638 | E49: 6353291 | F49: 7456393 | G49: 11299131 | H49: 5223005 | I49: 5223005 | J49: 11005255 | K49: 7227239 | L49: 18940470 | M49: 18940470 | N49: 18940470 | O49: 18940470 | P49: 18940470 | Q49: 18940470 | R49: 18940470 | S49: 18940470
A50: 仕入債務合計 | B50: =VLOOKUP(A50,Sheet1!$A$1:$B$242,2,FALSE) -> 매입채무합계 | C50: 13016963 | D50: 6730638 | E50: 6353291 | F50: 7456393 | G50: 11299131 | H50: 5223005 | I50: 5223005 | J50: 11005255 | K50: 7227239 | L50: 18940470 | M50: 18940470 | N50: 18940470 | O50: 18940470 | P50: 18940470 | Q50: 18940470 | R50: 18940470 | S50: 18940470
A51: [他流動負債] | B51: =VLOOKUP(A51,Sheet1!$A$1:$B$242,2,FALSE) -> [기타유동부채]
A52: 短期借入金 | B52: =VLOOKUP(A52,Sheet1!$A$1:$B$242,2,FALSE) -> 단기차입금 | C52: 10864000 | D52: 9506000 | E52: 8148000 | F52: 6790000 | G52: 5432000 | H52: 4074000 | I52: 4074000 | J52: 2716000 | K52: 1358000 | L52: 34256000 | M52: 34256000 | N52: 34256000 | O52: 34256000 | P52: 34256000 | Q52: 34256000 | R52: 34256000 | S52: 34256000
A53: 未払金 | B53: =VLOOKUP(A53,Sheet1!$A$1:$B$242,2,FALSE) -> 미불금 | C53: 31686710 | D53: 30642815 | E53: 28252416 | F53: 24983068 | G53: 24506787 | H53: 21161103 | I53: 21161103 | J53: 20345226 | K53: 20972250 | L53: 32057622 | M53: 32057622 | N53: 32057622 | O53: 32057622 | P53: 32057622 | Q53: 32057622 | R53: 32057622 | S53: 32057622
A54: 未払費用 | B54: =VLOOKUP(A54,Sheet1!$A$1:$B$242,2,FALSE) -> 미불비용 | C54: 4124473 | D54: 3869174 | E54: 3410592 | F54: 4237831 | G54: 4053033 | H54: 4020947 | I54: 4020947 | J54: 4082544 | K54: 4470580 | L54: 5191197 | M54: 5191197 | N54: 5191197 | O54: 5191197 | P54: 5191197 | Q54: 5191197 | R54: 5191197 | S54: 5191197
A55: 未払法人税等 | B55: =VLOOKUP(A55,Sheet1!$A$1:$B$242,2,FALSE) -> 미불법인세등 | C55: 310000 | D55: 310000 | E55: 0 | F55: 0 | G55: 0 | H55: 0 | I55: 0 | J55: 0 | K55: 0 | L55: 210800 | M55: 210800 | N55: 210800 | O55: 210800 | P55: 210800 | Q55: 210800 | R55: 210800 | S55: 210800
A56: 未払消費税等 | B56: =VLOOKUP(A56,Sheet1!$A$1:$B$242,2,FALSE) -> 미불소비세 | C56: 7388000 | D56: 7288000 | E56: 6488000 | F56: 5688000 | G56: 5400000 | H56: 4600000 | I56: 4600000 | J56: 3800000 | K56: 3600000 | L56: 15870600 | M56: 15870600 | N56: 15870600 | O56: 15870600 | P56: 15870600 | Q56: 15870600 | R56: 15870600 | S56: 15870600
A57: 前受金 | B57: =VLOOKUP(A57,Sheet1!$A$1:$B$242,2,FALSE) -> 전수금 | C57: 0 | D57: 0 | E57: 0 | F57: 0 | G57: 96590 | H57: 69660 | I57: 69660 | J57: 54830 | K57: 53990 | L57: 52210 | M57: 52210 | N57: 52210 | O57: 52210 | P57: 52210 | Q57: 52210 | R57: 52210 | S57: 52210
A58: 預り金 | B58: =VLOOKUP(A58,Sheet1!$A$1:$B$242,2,FALSE) -> 예수금 | C58: 2623774 | D58: 2364598 | E58: 2207852 | F58: 2319349 | G58: 2732799 | H58: 2080450 | I58: 2080450 | J58: 2202876 | K58: 2088532 | L58: 1949202 | M58: 1949202 | N58: 1949202 | O58: 1949202 | P58: 1949202 | Q58: 1949202 | R58: 1949202 | S58: 1949202
A59: 仮受金 | B59: =VLOOKUP(A59,Sheet1!$A$1:$B$242,2,FALSE) -> 가수금 | C59: 0 | D59: 0 | E59: 0 | F59: 0 | G59: 0 | H59: 0 | I59: 0 | J59: 0 | K59: 0 | L59: 0 | M59: 0 | N59: 0 | O59: 0 | P59: 0 | Q59: 0 | R59: 0 | S59: 0
A60: 仮受消費税等 | B60: =VLOOKUP(A60,Sheet1!$A$1:$B$242,2,FALSE) -> 소비세예수금 | C60: 3323416 | D60: 6820885 | E60: 11654311 | F60: 15849295 | G60: 19649218 | H60: 25787019 | I60: 25787019 | J60: 31398903 | K60: 37419146 | L60: 0 | M60: 0 | N60: 0 | O60: 0 | P60: 0 | Q60: 0 | R60: 0 | S60: 0
A61: 他流動負債合計 | B61: =VLOOKUP(A61,Sheet1!$A$1:$B$242,2,FALSE) -> 기타유동부채합계 | C61: 60320373 | D61: 60801472 | E61: 60161171 | F61: 59867543 | G61: 61870427 | H61: 61793179 | I61: 61793179 | J61: 64600379 | K61: 69962498 | L61: 89587631 | M61: 89587631 | N61: 89587631 | O61: 89587631 | P61: 89587631 | Q61: 89587631 | R61: 89587631 | S61: 89587631
A62: 流動負債合計 | B62: =VLOOKUP(A62,Sheet1!$A$1:$B$242,2,FALSE) -> 유동부채합계 | C62: 73337336 | D62: 67532110 | E62: 66514462 | F62: 67323936 | G62: 73169558 | H62: 67016184 | I62: 67016184 | J62: 75605634 | K62: 77189737 | L62: 108528101 | M62: 108528101 | N62: 108528101 | O62: 108528101 | P62: 108528101 | Q62: 108528101 | R62: 108528101 | S62: 108528101
A63: [固定負債] | B63: =VLOOKUP(A63,Sheet1!$A$1:$B$242,2,FALSE) -> [고정부채]
A64: 長期借入金 | B64: =VLOOKUP(A64,Sheet1!$A$1:$B$242,2,FALSE) -> 장기차입금 | C64: 41644000 | D64: 41644000 | E64: 41644000 | F64: 41644000 | G64: 41644000 | H64: 41644000 | I64: 41644000 | J64: 41644000 | K64: 41644000 | L64: 7388000 | M64: 7388000 | N64: 7388000 | O64: 7388000 | P64: 7388000 | Q64: 7388000 | R64: 7388000 | S64: 7388000
A65: 長期未払金 | B65: =VLOOKUP(A65,Sheet1!$A$1:$B$242,2,FALSE) -> 장기미불금 | C65: 10243027 | D65: 10243027 | E65: 10243027 | F65: 10243027 | G65: 10243027 | H65: 10243027 | I65: 10243027 | J65: 10243027 | K65: 10243027 | L65: 3624800 | M65: 3624800 | N65: 3624800 | O65: 3624800 | P65: 3624800 | Q65: 3624800 | R65: 3624800 | S65: 3624800
A66: 固定負債合計 | B66: =VLOOKUP(A66,Sheet1!$A$1:$B$242,2,FALSE) -> 고정부채합계 | C66: 51887027 | D66: 51887027 | E66: 51887027 | F66: 51887027 | G66: 51887027 | H66: 51887027 | I66: 51887027 | J66: 51887027 | K66: 51887027 | L66: 11012800 | M66: 11012800 | N66: 11012800 | O66: 11012800 | P66: 11012800 | Q66: 11012800 | R66: 11012800 | S66: 11012800
A67: 負債合計 | B67: =VLOOKUP(A67,Sheet1!$A$1:$B$242,2,FALSE) -> 부채합계 | C67: 125224363 | D67: 119419137 | E67: 118401489 | F67: 119210963 | G67: 125056585 | H67: 118903211 | I67: 118903211 | J67: 127492661 | K67: 129076764 | L67: 119540901 | M67: 119540901 | N67: 119540901 | O67: 119540901 | P67: 119540901 | Q67: 119540901 | R67: 119540901 | S67: 119540901
A68: [資本金] | B68: =VLOOKUP(A68,Sheet1!$A$1:$B$242,2,FALSE) -> [자본금]
A69: 資本金 | B69: =VLOOKUP(A69,Sheet1!$A$1:$B$242,2,FALSE) -> 자본금 | C69: 19999000 | D69: 19999000 | E69: 19999000 | F69: 19999000 | G69: 19999000 | H69: 19999000 | I69: 19999000 | J69: 19999000 | K69: 19999000 | L69: 19999000 | M69: 19999000 | N69: 19999000 | O69: 19999000 | P69: 19999000 | Q69: 19999000 | R69: 19999000 | S69: 19999000
A70: 資本金合計 | B70: =VLOOKUP(A70,Sheet1!$A$1:$B$242,2,FALSE) -> 자본금합계 | C70: 19999000 | D70: 19999000 | E70: 19999000 | F70: 19999000 | G70: 19999000 | H70: 19999000 | I70: 19999000 | J70: 19999000 | K70: 19999000 | L70: 19999000 | M70: 19999000 | N70: 19999000 | O70: 19999000 | P70: 19999000 | Q70: 19999000 | R70: 19999000 | S70: 19999000
A71: [新株式申込証拠金] | B71: =VLOOKUP(A71,Sheet1!$A$1:$B$242,2,FALSE) -> [신주발행준비금]
A72: 新株式申込証拠金合計 | B72: =VLOOKUP(A72,Sheet1!$A$1:$B$242,2,FALSE) -> 신주발행준비금합계 | C72: 0 | D72: 0 | E72: 0 | F72: 0 | G72: 0 | H72: 0 | I72: 0 | J72: 0 | K72: 0 | L72: 0 | M72: 0 | N72: 0 | O72: 0 | P72: 0 | Q72: 0 | R72: 0 | S72: 0
A73: [資本剰余金] | B73: =VLOOKUP(A73,Sheet1!$A$1:$B$242,2,FALSE) -> [자본금잉여금]
A74: 資本準備金合計 | B74: =VLOOKUP(A74,Sheet1!$A$1:$B$242,2,FALSE) -> 자본준비금합계 | C74: 0 | D74: 0 | E74: 0 | F74: 0 | G74: 0 | H74: 0 | I74: 0 | J74: 0 | K74: 0 | L74: 0 | M74: 0 | N74: 0 | O74: 0 | P74: 0 | Q74: 0 | R74: 0 | S74: 0
A75: その他資本剰余金合計 | B75: =VLOOKUP(A75,Sheet1!$A$1:$B$242,2,FALSE) -> 기타자본잉여금합계 | C75: 0 | D75: 0 | E75: 0 | F75: 0 | G75: 0 | H75: 0 | I75: 0 | J75: 0 | K75: 0 | L75: 0 | M75: 0 | N75: 0 | O75: 0 | P75: 0 | Q75: 0 | R75: 0 | S75: 0
A76: 資本剰余金合計 | B76: =VLOOKUP(A76,Sheet1!$A$1:$B$242,2,FALSE) -> 자본잉여금 합계 | C76: 0 | D76: 0 | E76: 0 | F76: 0 | G76: 0 | H76: 0 | I76: 0 | J76: 0 | K76: 0 | L76: 0 | M76: 0 | N76: 0 | O76: 0 | P76: 0 | Q76: 0 | R76: 0 | S76: 0
A77: [利益剰余金] | B77: =VLOOKUP(A77,Sheet1!$A$1:$B$242,2,FALSE) -> [이익잉여금]
A78: 利益準備金合計 | B78: =VLOOKUP(A78,Sheet1!$A$1:$B$242,2,FALSE) -> 이익준비금합계 | C78: 0 | D78: 0 | E78: 0 | F78: 0 | G78: 0 | H78: 0 | I78: 0 | J78: 0 | K78: 0 | L78: 0 | M78: 0 | N78: 0 | O78: 0 | P78: 0 | Q78: 0 | R78: 0 | S78: 0
A79: 任意積立金合計 | B79: =VLOOKUP(A79,Sheet1!$A$1:$B$242,2,FALSE) -> 임의적립금 합계 | C79: 0 | D79: 0 | E79: 0 | F79: 0 | G79: 0 | H79: 0 | I79: 0 | J79: 0 | K79: 0 | L79: 0 | M79: 0 | N79: 0 | O79: 0 | P79: 0 | Q79: 0 | R79: 0 | S79: 0
A80: 繰越利益 | B80: =VLOOKUP(A80,Sheet1!$A$1:$B$242,2,FALSE) -> 이월이익 | C80: -20052175 | D80: -20052175 | E80: -20052175 | F80: -20052175 | G80: -20052175 | H80: -20052175 | I80: -20052175 | J80: -20052175 | K80: -20052175 | L80: -20052175 | M80: -20052175 | N80: -20052175 | O80: -20052175 | P80: -20052175 | Q80: -20052175 | R80: -20052175 | S80: -20052175
A81: 当期純損益金額 | B81: =VLOOKUP(A81,Sheet1!$A$1:$B$242,2,FALSE) -> 당기순손익금액 | C81: 1381208 | D81: 4736843 | E81: 14739699 | F81: 20385508 | G81: 22751640 | H81: 33743479 | I81: 33743479 | J81: 46282531 | K81: 53422417 | L81: 90067828 | M81: 90067828 | N81: 90067828 | O81: 90067828 | P81: 90067828 | Q81: 90067828 | R81: 90067828 | S81: 90067828
A82: 繰越利益剰余金合計 | B82: =VLOOKUP(A82,Sheet1!$A$1:$B$242,2,FALSE) -> 이월이익잉여금합계 | C82: -18670967 | D82: -15315332 | E82: -5312476 | F82: 333333 | G82: 2699465 | H82: 13691304 | I82: 13691304 | J82: 26230356 | K82: 33370242 | L82: 70015653 | M82: 70015653 | N82: 70015653 | O82: 70015653 | P82: 70015653 | Q82: 70015653 | R82: 70015653 | S82: 70015653
A83: その他利益剰余金合計 | B83: =VLOOKUP(A83,Sheet1!$A$1:$B$242,2,FALSE) -> 기타이익잉여금합계 | C83: -18670967 | D83: -15315332 | E83: -5312476 | F83: 333333 | G83: 2699465 | H83: 13691304 | I83: 13691304 | J83: 26230356 | K83: 33370242 | L83: 70015653 | M83: 70015653 | N83: 70015653 | O83: 70015653 | P83: 70015653 | Q83: 70015653 | R83: 70015653 | S83: 70015653
A84: 利益剰余金合計 | B84: =VLOOKUP(A84,Sheet1!$A$1:$B$242,2,FALSE) -> 이익잉여금합계 | C84: -18670967 | D84: -15315332 | E84: -5312476 | F84: 333333 | G84: 2699465 | H84: 13691304 | I84: 13691304 | J84: 26230356 | K84: 33370242 | L84: 70015653 | M84: 70015653 | N84: 70015653 | O84: 70015653 | P84: 70015653 | Q84: 70015653 | R84: 70015653 | S84: 70015653
A85: [自己株式] | B85: =VLOOKUP(A85,Sheet1!$A$1:$B$242,2,FALSE) -> [자기자본]
A86: 自己株式合計 | B86: =VLOOKUP(A86,Sheet1!$A$1:$B$242,2,FALSE) -> 자기자본합계 | C86: 0 | D86: 0 | E86: 0 | F86: 0 | G86: 0 | H86: 0 | I86: 0 | J86: 0 | K86: 0 | L86: 0 | M86: 0 | N86: 0 | O86: 0 | P86: 0 | Q86: 0 | R86: 0 | S86: 0
A87: [自己株式申込証拠金] | B87: =VLOOKUP(A87,Sheet1!$A$1:$B$242,2,FALSE) -> [자기주식발행준비금]
A88: 自己株式申込証拠金合計 | B88: =VLOOKUP(A88,Sheet1!$A$1:$B$242,2,FALSE) -> 자기주식발행준비금합계 | C88: 0 | D88: 0 | E88: 0 | F88: 0 | G88: 0 | H88: 0 | I88: 0 | J88: 0 | K88: 0 | L88: 0 | M88: 0 | N88: 0 | O88: 0 | P88: 0 | Q88: 0 | R88: 0 | S88: 0
A89: 株主資本合計 | B89: =VLOOKUP(A89,Sheet1!$A$1:$B$242,2,FALSE) -> 주주자본합계 | C89: 1328033 | D89: 4683668 | E89: 14686524 | F89: 20332333 | G89: 22698465 | H89: 33690304 | I89: 33690304 | J89: 46229356 | K89: 53369242 | L89: 90014653 | M89: 90014653 | N89: 90014653 | O89: 90014653 | P89: 90014653 | Q89: 90014653 | R89: 90014653 | S89: 90014653
A90: [評価･換算差額等] | B90: =VLOOKUP(A90,Sheet1!$A$1:$B$242,2,FALSE) -> [평가･환산차액등]
A91: 評価･換算差額等合計 | B91: =VLOOKUP(A91,Sheet1!$A$1:$B$242,2,FALSE) -> 평가･환산차액등합계 | C91: 0 | D91: 0 | E91: 0 | F91: 0 | G91: 0 | H91: 0 | I91: 0 | J91: 0 | K91: 0 | L91: 0 | M91: 0 | N91: 0 | O91: 0 | P91: 0 | Q91: 0 | R91: 0 | S91: 0
A92: [新株予約権] | B92: =VLOOKUP(A92,Sheet1!$A$1:$B$242,2,FALSE) -> [신주예약권]
A93: 新株予約権合計 | B93: =VLOOKUP(A93,Sheet1!$A$1:$B$242,2,FALSE) -> 신주예약권합계 | C93: 0 | D93: 0 | E93: 0 | F93: 0 | G93: 0 | H93: 0 | I93: 0 | J93: 0 | K93: 0 | L93: 0 | M93: 0 | N93: 0 | O93: 0 | P93: 0 | Q93: 0 | R93: 0 | S93: 0
A94: 純資産合計 | B94: =VLOOKUP(A94,Sheet1!$A$1:$B$242,2,FALSE) -> 순자산합계 | C94: 1328033 | D94: 4683668 | E94: 14686524 | F94: 20332333 | G94: 22698465 | H94: 33690304 | I94: 33690304 | J94: 46229356 | K94: 53369242 | L94: 90014653 | M94: 90014653 | N94: 90014653 | O94: 90014653 | P94: 90014653 | Q94: 90014653 | R94: 90014653 | S94: 90014653
A95: 負債･純資産合計 | B95: =VLOOKUP(A95,Sheet1!$A$1:$B$242,2,FALSE) -> 부채･순자산합계 | C95: 126552396 | D95: 124102805 | E95: 133088013 | F95: 139543296 | G95: 147755050 | H95: 152593515 | I95: 152593515 | J95: 173722017 | K95: 182446006 | L95: 209555554 | M95: 209555554 | N95: 209555554 | O95: 209555554 | P95: 209555554 | Q95: 209555554 | R95: 209555554 | S95: 209555554

Sheet PL
A1: 帳票名：残高試算表(年間推移)
A3: 事業所名：株式会社マザースマイル
A4: 税抜/税込：税抜
A6: 勘定科目 | B6: =VLOOKUP(A6,Sheet1!$A$1:$B$242,2,FALSE) -> 계정과목 | C6: 4月度 | D6: 5月度 | E6: 6月度 | F6: 7月度 | G6: 8月度 | H6: 9月度 | I6: 上半期残高(合計) | J6: 10月度 | K6: 11月度 | L6: 12月度 | M6: 1月度 | N6: 2月度 | O6: 3月度 | P6: 下半期残高(合計) | Q6: 当期仮残高(合計) | R6: 決算残高(合計) | S6: 当期残高(合計)
A7: [売上高] | B7: =VLOOKUP(A7,Sheet1!$A$1:$B$242,2,FALSE) -> [매출]
A8: 売上高 | B8: =VLOOKUP(A8,Sheet1!$A$1:$B$242,2,FALSE) -> 매출 | C8: 33690019 | D8: 35539299 | E8: 49636275 | F8: 42213072 | G8: 38221057 | H8: 62293873 | I8: 261593595 | J8: 55454255 | K8: 60410575 | L8: 97751542 | M8: 0 | N8: 0 | O8: 0 | P8: 213616372 | Q8: 475209967 | R8: 0 | S8: 475209967
A9: 売上戻り高 | B9: =VLOOKUP(A9,Sheet1!$A$1:$B$242,2,FALSE) -> 매출환입 | C9: 398597 | D9: 263602 | E9: 179902 | F9: 245075 | G9: 116290 | H9: 186517 | I9: 1389983 | J9: 238452 | K9: 259314 | L9: 366735 | M9: 0 | N9: 0 | O9: 0 | P9: 864501 | Q9: 2254484 | R9: 0 | S9: 2254484
A10: 売上高合計 | B10: =VLOOKUP(A10,Sheet1!$A$1:$B$242,2,FALSE) -> 매출합계 | C10: 33291422 | D10: 35275697 | E10: 49456373 | F10: 41967997 | G10: 38104767 | H10: 62107356 | I10: 260203612 | J10: 55215803 | K10: 60151261 | L10: 97384807 | M10: 0 | N10: 0 | O10: 0 | P10: 212751871 | Q10: 472955483 | R10: 0 | S10: 472955483
A11: [売上原価] | B11: =VLOOKUP(A11,Sheet1!$A$1:$B$242,2,FALSE) -> [매출원가]
A12: 期首商品棚卸高 | B12: =VLOOKUP(A12,Sheet1!$A$1:$B$242,2,FALSE) -> 기초상품재고액 | C12: 72910492 | D12: 75443317 | E12: 72214523 | F12: 63829945 | G12: 68176813 | H12: 67522901 | I12: 420097991 | J12: 47297814 | K12: 58667847 | L12: -453153160 | M12: 0 | N12: 0 | O12: 0 | P12: -347187499 | Q12: 72910492 | R12: 0 | S12: 72910492
A13: 期首商品棚卸高 | B13: =VLOOKUP(A13,Sheet1!$A$1:$B$242,2,FALSE) -> 기초상품재고액 | C13: 72910492 | D13: 75443317 | E13: 72214523 | F13: 63829945 | G13: 68176813 | H13: 67522901 | I13: 420097991 | J13: 47297814 | K13: 58667847 | L13: -453153160 | M13: 0 | N13: 0 | O13: 0 | P13: -347187499 | Q13: 72910492 | R13: 0 | S13: 72910492
A14: 仕入高 | B14: =VLOOKUP(A14,Sheet1!$A$1:$B$242,2,FALSE) -> 매입 | C14: 16061711 | D14: 10191346 | E14: 12106070 | F14: 21140128 | G14: 13143000 | H14: 8817768 | I14: 81460023 | J14: 32489688 | K14: 29002842 | L14: 36781672 | M14: 0 | N14: 0 | O14: 0 | P14: 98274202 | Q14: 179734225 | R14: 0 | S14: 179734225
A15: 仕入諸掛費 | B15: =VLOOKUP(A15,Sheet1!$A$1:$B$242,2,FALSE) -> 매입제비용 | C15: 1476872 | D15: 1121690 | E15: 1143317 | F15: 1235990 | G15: 1326417 | H15: 977990 | I15: 7282276 | J15: 2348382 | K15: 2926291 | L15: 3139535 | M15: 0 | N15: 0 | O15: 0 | P15: 8414208 | Q15: 15696484 | R15: 0 | S15: 15696484
A16: 当期商品仕入高 | B16: =VLOOKUP(A16,Sheet1!$A$1:$B$242,2,FALSE) -> 당기상품매입액 | C16: 17538583 | D16: 11313036 | E16: 13249387 | F16: 22376118 | G16: 14469417 | H16: 9795758 | I16: 88742299 | J16: 34838070 | K16: 31929133 | L16: 39921207 | M16: 0 | N16: 0 | O16: 0 | P16: 106688410 | Q16: 195430709 | R16: 0 | S16: 195430709
A17: 合計 | B17: =VLOOKUP(A17,Sheet1!$A$1:$B$242,2,FALSE) -> 합계 | C17: 90449075 | D17: 86756353 | E17: 85463910 | F17: 86206063 | G17: 82646230 | H17: 77318659 | I17: 508840290 | J17: 82135884 | K17: 90596980 | L17: -413231953 | M17: 0 | N17: 0 | O17: 0 | P17: -240499089 | Q17: 268341201 | R17: 0 | S17: 268341201
A18: 他勘定振替高(商) | B18: =VLOOKUP(A18,Sheet1!$A$1:$B$242,2,FALSE) -> 타계정전환 | C18: 348345 | D18: 312040 | E18: 203213 | F18: 321465 | G18: 332494 | H18: 398587 | I18: 1916144 | J18: 613306 | K18: 590023 | L18: 510941 | M18: 0 | N18: 0 | O18: 0 | P18: 1714270 | Q18: 3630414 | R18: 0 | S18: 3630414
A19: 期末商品棚卸高 | B19: =VLOOKUP(A19,Sheet1!$A$1:$B$242,2,FALSE) -> 기말상품재고액 | C19: 75443317 | D19: 72214523 | E19: 63829945 | F19: 68176813 | G19: 67522901 | H19: 47297814 | I19: 394485313 | J19: 58667847 | K19: 61842456 | L19: -442362742 | M19: 0 | N19: 0 | O19: 0 | P19: -321852439 | Q19: 72632874 | R19: 0 | S19: 72632874
A20: 期末商品棚卸高 | B20: =VLOOKUP(A20,Sheet1!$A$1:$B$242,2,FALSE) -> 기말상품재고액 | C20: 75443317 | D20: 72214523 | E20: 63829945 | F20: 68176813 | G20: 67522901 | H20: 47297814 | I20: 394485313 | J20: 58667847 | K20: 61842456 | L20: -442362742 | M20: 0 | N20: 0 | O20: 0 | P20: -321852439 | Q20: 72632874 | R20: 0 | S20: 72632874
A21: 売上原価 | B21: =VLOOKUP(A21,Sheet1!$A$1:$B$242,2,FALSE) -> 매출원가 | C21: 14657413 | D21: 14229790 | E21: 21430752 | F21: 17707785 | G21: 14790835 | H21: 29622258 | I21: 112438833 | J21: 22854731 | K21: 28164501 | L21: 28619848 | M21: 0 | N21: 0 | O21: 0 | P21: 79639080 | Q21: 192077913 | R21: 0 | S21: 192077913
A22: 売上総損益金額 | B22: =VLOOKUP(A22,Sheet1!$A$1:$B$242,2,FALSE) -> 매출총손익금액 | C22: 18634009 | D22: 21045907 | E22: 28025621 | F22: 24260212 | G22: 23313932 | H22: 32485098 | I22: 147764779 | J22: 32361072 | K22: 31986760 | L22: 68764959 | M22: 0 | N22: 0 | O22: 0 | P22: 133112791 | Q22: 280877570 | R22: 0 | S22: 280877570
A23: [販売管理費] | B23: =VLOOKUP(A23,Sheet1!$A$1:$B$242,2,FALSE) -> [판매관리비]
A24: 役員報酬 | B24: =VLOOKUP(A24,Sheet1!$A$1:$B$242,2,FALSE) -> 임원보수 | C24: 3998480 | D24: 3571440 | E24: 3571432 | F24: 3571432 | G24: 3571432 | H24: 3571432 | I24: 21855648 | J24: 3571432 | K24: 3571440 | L24: 3571432 | M24: 0 | N24: 0 | O24: 0 | P24: 10714304 | Q24: 32569952 | R24: 0 | S24: 32569952
A25: 給料手当 | B25: =VLOOKUP(A25,Sheet1!$A$1:$B$242,2,FALSE) -> 급여수당 | C25: 3163971 | D25: 2559049 | E25: 2364237 | F25: 3244017 | G25: 2913737 | H25: 2985857 | I25: 17230868 | J25: 3175237 | K25: 3405637 | L25: 3480263 | M25: 0 | N25: 0 | O25: 0 | P25: 10061137 | Q25: 27292005 | R25: 0 | S25: 27292005
A26: 雑給 | B26: =VLOOKUP(A26,Sheet1!$A$1:$B$242,2,FALSE) -> 잡급 | C26: 0 | D26: 0 | E26: 129000 | F26: 0 | G26: 217000 | H26: 0 | I26: 346000 | J26: 0 | K26: 241000 | L26: 230000 | M26: 0 | N26: 0 | O26: 0 | P26: 471000 | Q26: 817000 | R26: 0 | S26: 817000
A27: 賞与 | B27: =VLOOKUP(A27,Sheet1!$A$1:$B$242,2,FALSE) -> 상여 | C27: 253740 | D27: 0 | E27: 0 | F27: 0 | G27: 2249854 | H27: 0 | I27: 2503594 | J27: 210422 | K27: 0 | L27: 0 | M27: 0 | N27: 0 | O27: 0 | P27: 210422 | Q27: 2714016 | R27: 0 | S27: 2714016
A28: 法定福利費 | B28: =VLOOKUP(A28,Sheet1!$A$1:$B$242,2,FALSE) -> 법정복리비 | C28: 739876 | D28: 615470 | E28: 583595 | F28: 626960 | G28: 655710 | H28: 1089194 | I28: 4310805 | J28: 555901 | K28: 766589 | L28: 647031 | M28: 0 | N28: 0 | O28: 0 | P28: 1969521 | Q28: 6280326 | R28: 0 | S28: 6280326
A29: 福利厚生費 | B29: =VLOOKUP(A29,Sheet1!$A$1:$B$242,2,FALSE) -> 복리후생비 | C29: 0 | D29: 0 | E29: 18000 | F29: 4802 | G29: 0 | H29: 0 | I29: 22802 | J29: 18000 | K29: 8889 | L29: 521308 | M29: 0 | N29: 0 | O29: 0 | P29: 548197 | Q29: 570999 | R29: 0 | S29: 570999
A30: 外注費 | B30: =VLOOKUP(A30,Sheet1!$A$1:$B$242,2,FALSE) -> 외주비 | C30: 936289 | D30: 1715717 | E30: 1401132 | F30: 566904 | G30: 578000 | H30: 381400 | I30: 5579442 | J30: 445000 | K30: 421040 | L30: 477000 | M30: 0 | N30: 0 | O30: 0 | P30: 1343040 | Q30: 6922482 | R30: 0 | S30: 6922482
A31: 荷造運賃 | B31: =VLOOKUP(A31,Sheet1!$A$1:$B$242,2,FALSE) -> 운반비 | C31: 2119024 | D31: 1964961 | E31: 1987110 | F31: 1984855 | G31: 1725344 | H31: 2799677 | I31: 12580971 | J31: 2162415 | K31: 2374825 | L31: 3220352 | M31: 0 | N31: 0 | O31: 0 | P31: 7757592 | Q31: 20338563 | R31: 0 | S31: 20338563
A32: 広告宣伝費 | B32: =VLOOKUP(A32,Sheet1!$A$1:$B$242,2,FALSE) -> 광고선전비 | C32: 406744 | D32: 422827 | E32: 251962 | F32: 354093 | G32: 383164 | H32: 495154 | I32: 2313944 | J32: 704554 | K32: 1008552 | L32: 857523 | M32: 0 | N32: 0 | O32: 0 | P32: 2570629 | Q32: 4884573 | R32: 0 | S32: 4884573
A33: 交際費 | B33: =VLOOKUP(A33,Sheet1!$A$1:$B$242,2,FALSE) -> 교제비 | C33: 17828 | D33: 87433 | E33: 157134 | F33: 146220 | G33: 124059 | H33: 59884 | I33: 592558 | J33: 60292 | K33: 126407 | L33: 433760 | M33: 0 | N33: 0 | O33: 0 | P33: 620459 | Q33: 1213017 | R33: 0 | S33: 1213017
A34: 会議費 | B34: =VLOOKUP(A34,Sheet1!$A$1:$B$242,2,FALSE) -> 회의비 | C34: 105451 | D34: 53153 | E34: 128458 | F34: 173989 | G34: 175839 | H34: 111624 | I34: 748514 | J34: 122400 | K34: 224884 | L34: 404363 | M34: 0 | N34: 0 | O34: 0 | P34: 751647 | Q34: 1500161 | R34: 0 | S34: 1500161
A35: 旅費交通費 | B35: =VLOOKUP(A35,Sheet1!$A$1:$B$242,2,FALSE) -> 여비교통비 | C35: 102341 | D35: 123173 | E35: 188819 | F35: 234414 | G35: 175552 | H35: 248471 | I35: 1072770 | J35: 230313 | K35: 1248449 | L35: 2749730 | M35: 0 | N35: 0 | O35: 0 | P35: 4228492 | Q35: 5301262 | R35: 0 | S35: 5301262
... A53: 営業損益金額 | B53: =VLOOKUP(A53,Sheet1!$A$1:$B$242,2,FALSE) -> 영업손익금액 | C53: 1490216 | D53: 3016360 | E53: 10064647 | F53: 5475659 | G53: 2498617 | H53: 11240370 | I53: 33785869 | J53: 11630331 | K53: 7607757 | L53: 36954409 | M53: 0 | N53: 0 | O53: 0 | P53: 56192497 | Q53: 89978366 | R53: 0 | S53: 89978366
A54: [営業外収益] | B54: =VLOOKUP(A54,Sheet1!$A$1:$B$242,2,FALSE) -> [영업외수익]
A56: 受取利息 | B56: =VLOOKUP(A56,Sheet1!$A$1:$B$242,2,FALSE) -> 이자수익 | C56: 0 | D56: 0 | E56: 0 | F56: 0 | G56: 8043 | H56: 0 | I56: 8043 | J56: 0 | K56: 0 | L56: 0 | M56: 0 | N56: 0 | O56: 0 | P56: 0 | Q56: 8043 | R56: 0 | S56: 8043
A57: 貸倒引当金戻入額 | B57: =VLOOKUP(A57,Sheet1!$A$1:$B$242,2,FALSE) -> 대손충당금 환입액 | C57: 0 | D57: 0 | E57: 0 | F57: 0 | G57: 0 | H57: 0 | I57: 0 | J57: 0 | K57: 0 | L57: 206241 | M57: 0 | N57: 0 | O57: 0 | P57: 206241 | Q57: 206241 | R57: 0 | S57: 206241
A58: 雑収入 | B58: =VLOOKUP(A58,Sheet1!$A$1:$B$242,2,FALSE) -> 잡수익 | C58: 113037 | D58: 569628 | E58: 106430 | F58: 681367 | G58: -360545 | H58: 176120 | I58: 1286037 | J58: 333123 | K58: 235671 | L58: 39944 | M58: 0 | N58: 0 | O58: 0 | P58: 608738 | Q58: 1894775 | R58: 0 | S58: 1894775
A59: 営業外収益合計 | B59: =VLOOKUP(A59,Sheet1!$A$1:$B$242,2,FALSE) -> 영업외수익합계 | C59: 113037 | D59: 569628 | E59: 106430 | F59: 681367 | G59: -352502 | H59: 176120 | I59: 1294080 | J59: 333123 | K59: 235671 | L59: 246185 | M59: 0 | N59: 0 | O59: 0 | P59: 814979 | Q59: 2109059 | R59: 0 | S59: 2109059
A60: [営業外費用] | B60: =VLOOKUP(A60,Sheet1!$A$1:$B$242,2,FALSE) -> [영업외비용]
A61: 支払利息 | B61: =VLOOKUP(A61,Sheet1!$A$1:$B$242,2,FALSE) -> 지급이자 | C61: 43401 | D61: 42272 | E61: 41378 | F61: 39092 | G61: 36332 | H61: 36917 | I61: 239392 | J61: 33617 | K61: 30424 | L61: 260549 | M61: 0 | N61: 0 | O61: 0 | P61: 324590 | Q61: 563982 | R61: 0 | S61: 563982
A62: 雑損失 | B62: =VLOOKUP(A62,Sheet1!$A$1:$B$242,2,FALSE) -> 잡손실 | C62: 178644 | D62: 188081 | E62: 126843 | F62: 472125 | G62: -257579 | H62: 387734 | I62: 1095848 | J62: 64830 | K62: 673118 | L62: 83834 | M62: 0 | N62: 0 | O62: 0 | P62: 821782 | Q62: 1917630 | R62: 0 | S62: 1917630
A63: 営業外費用合計 | B63: =VLOOKUP(A63,Sheet1!$A$1:$B$242,2,FALSE) -> 영업외비용합계 | C63: 222045 | D63: 230353 | E63: 168221 | F63: 511217 | G63: -221247 | H63: 424651 | I63: 1335240 | J63: 98447 | K63: 703542 | L63: 344383 | M63: 0 | N63: 0 | O63: 0 | P63: 1146372 | Q63: 2481612 | R63: 0 | S63: 2481612
A64: 経常損益金額 | B64: =VLOOKUP(A64,Sheet1!$A$1:$B$242,2,FALSE) -> 경상손익금액 | C64: 1381208 | D64: 3355635 | E64: 10002856 | F64: 5645809 | G64: 2367362 | H64: 10991839 | I64: 33744709 | J64: 11865007 | K64: 7139886 | L64: 36856211 | M64: 0 | N64: 0 | O64: 0 | P64: 55861104 | Q64: 89605813 | R64: 0 | S64: 89605813
A65: [特別利益] | B65: =VLOOKUP(A65,Sheet1!$A$1:$B$242,2,FALSE) -> [특별이익]
A66: 固定資産売却益 | B66: =VLOOKUP(A66,Sheet1!$A$1:$B$242,2,FALSE) -> 고정자산매각익 | C66: 0 | D66: 0 | E66: 0 | F66: 0 | G66: 0 | H66: 0 | I66: 0 | J66: 674046 | K66: 0 | L66: 0 | M66: 0 | N66: 0 | O66: 0 | P66: 674046 | Q66: 674046 | R66: 0 | S66: 674046
A67: 特別利益合計 | B67: =VLOOKUP(A67,Sheet1!$A$1:$B$242,2,FALSE) -> 특별이익합계 | C67: 0 | D67: 0 | E67: 0 | F67: 0 | G67: 0 | H67: 0 | I67: 0 | J67: 674046 | K67: 0 | L67: 0 | M67: 0 | N67: 0 | O67: 0 | P67: 674046 | Q67: 674046 | R67: 0 | S67: 674046
A68: [特別損失] | B68: =VLOOKUP(A68,Sheet1!$A$1:$B$242,2,FALSE) -> [특별손익]
A69: 固定資産売却損 | B69: =VLOOKUP(A69,Sheet1!$A$1:$B$242,2,FALSE) -> 고정자산매각손 | C69: 0 | D69: 0 | E69: 0 | F69: 0 | G69: 0 | H69: 0 | I69: 0 | J69: 1 | K69: 0 | L69: 0 | M69: 0 | N69: 0 | O69: 0 | P69: 1 | Q69: 1 | R69: 0 | S69: 1
A70: 特別損失合計 | B70: =VLOOKUP(A70,Sheet1!$A$1:$B$242,2,FALSE) -> 특별손실합계 | C70: 0 | D70: 0 | E70: 0 | F70: 0 | G70: 0 | H70: 0 | I70: 0 | J70: 1 | K70: 0 | L70: 0 | M70: 0 | N70: 0 | O70: 0 | P70: 1 | Q70: 1 | R70: 0 | S70: 1
A71: [当期純損益] | B71: =VLOOKUP(A71,Sheet1!$A$1:$B$242,2,FALSE) -> [당기순손익]
A72: 税引前当期純損益金額 | B72: =VLOOKUP(A72,Sheet1!$A$1:$B$242,2,FALSE) -> 법인세차감전순손익금액 | C72: 1381208 | D72: 3355635 | E72: 10002856 | F72: 5645809 | G72: 2367362 | H72: 10991839 | I72: 33744709 | J72: 12539052 | K72: 7139886 | L72: 36856211 | M72: 0 | N72: 0 | O72: 0 | P72: 56535149 | Q72: 90279858 | R72: 0 | S72: 90279858
A73: 法人税等 | B73: =VLOOKUP(A73,Sheet1!$A$1:$B$242,2,FALSE) -> 법인세등 | C73: 0 | D73: 0 | E73: 0 | F73: 0 | G73: 1230 | H73: 0 | I73: 1230 | J73: 0 | K73: 0 | L73: 210800 | M73: 0 | N73: 0 | O73: 0 | P73: 210800 | Q73: 212030 | R73: 0 | S73: 212030
A74: 当期純損益金額 | B74: =VLOOKUP(A74,Sheet1!$A$1:$B$242,2,FALSE) -> 당기순손익금액 | C74: 1381208 | D74: 3355635 | E74: 10002856 | F74: 5645809 | G74: 2366132 | H74: 10991839 | I74: 33743479 | J74: 12539052 | K74: 7139886 | L74: 36645411 | M74: 0 | N74: 0 | O74: 0 | P74: 56324349 | Q74: 90067828 | R74: 0 | S74: 90067828

Sheet Sheet1
A1: 勘定科目 | B1: 계정과목
A2: 相手勘定科目 | B2: 상대계정과목
A3: 諸口 | B3: 제좌
A4: [現金･預金] | B4: [현금･예금]
A5: 現金 | B5: 현금
A6: 普通預金 | B6: 보통예금
A7: 現金･預金合計 | B7: 현금 ･예금합계
A8: [売上債権] | B8: [매출채권]
A9: 売掛金 | B9: 외상매출금
A10: 売上債権合計 | B10: 매출채권합계
A11: [有価証券] | B11: [유가증권]
A12: 有価証券合計 | B12: 유가증권합계
... A168: 貸倒引当金繰入額(販) | B168: 대손충당금 설정액
